{
  "entrypoints": [
    "main"
  ],
  "origins": {
    "2237": [
      2237
    ],
    "2955": [
      1869,
      8401,
      2955
    ],
    "4662": [
      285,
      391,
      2079,
      2114,
      3560,
      4055,
      4230,
      4582,
      5475,
      5605,
      7252,
      8722,
      8746,
      9178,
      4662
    ],
    "9178": [
      285,
      391,
      2072,
      2079,
      2114,
      3560,
      3594,
      4015,
      4055,
      4230,
      4582,
      4662,
      4711,
      5475,
      5605,
      7252,
      8722,
      8746,
      9178
    ],
    "17896441": [
      1869,
      2955,
      8401
    ],
    "main": [
      1869,
      5354,
      8792
    ],
    "runtime~main": [
      1869,
      8792,
      5354
    ],
    "0058b4c6": [
      849
    ],
    "0152544b": [
      2866
    ],
    "0266a397": [
      489
    ],
    "05f37680": [
      6860
    ],
    "085c9425": [
      4662,
      9178,
      4055
    ],
    "1df93b7f": [
      4583
    ],
    "21c91d75": [
      5655
    ],
    "233375e9": [
      4662,
      9178,
      4230
    ],
    "24f52bd6": [
      3300
    ],
    "276632bd": [
      8463
    ],
    "2e9f3641": [
      7639
    ],
    "313b23b7": [
      6980
    ],
    "3720c009": [
      1869,
      4787
    ],
    "45475c54": [
      4662,
      9178,
      2114
    ],
    "4992fb8a": [
      2042
    ],
    "4a2ec5cd": [
      4662,
      9178,
      3560
    ],
    "4a9c656b": [
      2789
    ],
    "4ba3f97a": [
      4662,
      9178,
      8722
    ],
    "4f6c828f": [
      4172
    ],
    "566e4fb3": [
      6186
    ],
    "582942cb": [
      4498
    ],
    "5e95c892": [
      9647
    ],
    "612bf423": [
      9178,
      4711
    ],
    "7615d372": [
      942
    ],
    "763f1189": [
      4540
    ],
    "78ba771b": [
      4662,
      9178,
      8746
    ],
    "79b6951c": [
      2809
    ],
    "7ae10598": [
      1815
    ],
    "7dbdc362": [
      5570
    ],
    "898514b1": [
      9067
    ],
    "8a54e505": [
      9178,
      3594
    ],
    "8ae7243c": [
      9634
    ],
    "9113d538": [
      593
    ],
    "a373d53b": [
      9178,
      4015
    ],
    "a7456010": [
      1235
    ],
    "a7bd4aaa": [
      7098
    ],
    "a94703ab": [
      1869,
      9048
    ],
    "aba21aa0": [
      5742
    ],
    "aef901ed": [
      4188
    ],
    "b5b50283": [
      7946
    ],
    "bcaf8276": [
      4662,
      9178,
      4582
    ],
    "c47eb0e6": [
      4085
    ],
    "c5936f55": [
      4662,
      9178,
      5605
    ],
    "c6854a93": [
      4662,
      9178,
      7252
    ],
    "cdf69b89": [
      5950
    ],
    "de27da49": [
      4662,
      9178,
      391
    ],
    "df203c0f": [
      1869,
      4279
    ],
    "e01eb8b6": [
      9178,
      2072
    ],
    "e4a51e60": [
      3586
    ],
    "f5e764de": [
      4662,
      9178,
      5475
    ],
    "f857cf71": [
      7826
    ],
    "faef4eb3": [
      4662,
      9178,
      285
    ],
    "fdb40a7d": [
      4662,
      9178,
      2079
    ],
    "styles": [
      2955,
      4279,
      4787,
      5354,
      8401,
      8792,
      9048,
      1869
    ]
  },
  "assets": {
    "285": {
      "js": [
        {
          "file": "assets/js/faef4eb3.7f332412.js",
          "hash": "ec27c4376014b190",
          "publicPath": "/assets/js/faef4eb3.7f332412.js"
        }
      ]
    },
    "391": {
      "js": [
        {
          "file": "assets/js/de27da49.c93d8b48.js",
          "hash": "c292d50289de74d3",
          "publicPath": "/assets/js/de27da49.c93d8b48.js"
        }
      ]
    },
    "489": {
      "js": [
        {
          "file": "assets/js/0266a397.b2343add.js",
          "hash": "01e8dbfcb9a1000b",
          "publicPath": "/assets/js/0266a397.b2343add.js"
        }
      ]
    },
    "593": {
      "js": [
        {
          "file": "assets/js/9113d538.460e8350.js",
          "hash": "3a2cb4ca00f9fc8d",
          "publicPath": "/assets/js/9113d538.460e8350.js"
        }
      ]
    },
    "849": {
      "js": [
        {
          "file": "assets/js/0058b4c6.c30b6305.js",
          "hash": "2b45d5663b5bf120",
          "publicPath": "/assets/js/0058b4c6.c30b6305.js"
        }
      ]
    },
    "942": {
      "js": [
        {
          "file": "assets/js/7615d372.0c34b82b.js",
          "hash": "911cc5318395b292",
          "publicPath": "/assets/js/7615d372.0c34b82b.js"
        }
      ]
    },
    "1235": {
      "js": [
        {
          "file": "assets/js/a7456010.c4255ac9.js",
          "hash": "089793ba4f55e54a",
          "publicPath": "/assets/js/a7456010.c4255ac9.js"
        }
      ]
    },
    "1815": {
      "js": [
        {
          "file": "assets/js/7ae10598.28f17bba.js",
          "hash": "fd1346785e7cefdf",
          "publicPath": "/assets/js/7ae10598.28f17bba.js"
        }
      ]
    },
    "1869": {
      "css": [
        {
          "file": "assets/css/styles.c7051afe.css",
          "hash": "b0aafe35d0e28ff8",
          "publicPath": "/assets/css/styles.c7051afe.css"
        }
      ]
    },
    "2042": {
      "js": [
        {
          "file": "assets/js/4992fb8a.b5111261.js",
          "hash": "e4a9c2dfe923bc1f",
          "publicPath": "/assets/js/4992fb8a.b5111261.js"
        }
      ]
    },
    "2072": {
      "js": [
        {
          "file": "assets/js/e01eb8b6.f973b494.js",
          "hash": "68f9d5a004f93445",
          "publicPath": "/assets/js/e01eb8b6.f973b494.js"
        }
      ]
    },
    "2079": {
      "js": [
        {
          "file": "assets/js/fdb40a7d.42b41861.js",
          "hash": "9e481d32b0433a70",
          "publicPath": "/assets/js/fdb40a7d.42b41861.js"
        }
      ]
    },
    "2114": {
      "js": [
        {
          "file": "assets/js/45475c54.003af915.js",
          "hash": "c394b0dbd214569d",
          "publicPath": "/assets/js/45475c54.003af915.js"
        }
      ]
    },
    "2237": {
      "js": [
        {
          "file": "assets/js/2237.0ae39ba8.js",
          "hash": "1df49bb892db80e2",
          "publicPath": "/assets/js/2237.0ae39ba8.js"
        }
      ]
    },
    "2789": {
      "js": [
        {
          "file": "assets/js/4a9c656b.a3d0257a.js",
          "hash": "4f7772b26fc38bc6",
          "publicPath": "/assets/js/4a9c656b.a3d0257a.js"
        }
      ]
    },
    "2809": {
      "js": [
        {
          "file": "assets/js/79b6951c.5bb4a556.js",
          "hash": "aae35a6f17d15dc6",
          "publicPath": "/assets/js/79b6951c.5bb4a556.js"
        }
      ]
    },
    "2866": {
      "js": [
        {
          "file": "assets/js/0152544b.2cc4677e.js",
          "hash": "5e5c34d74dd22fea",
          "publicPath": "/assets/js/0152544b.2cc4677e.js"
        }
      ]
    },
    "2955": {
      "js": [
        {
          "file": "assets/js/2955.3e39e3ae.js",
          "hash": "45955ee2d4a4ea07",
          "publicPath": "/assets/js/2955.3e39e3ae.js"
        }
      ]
    },
    "3300": {
      "js": [
        {
          "file": "assets/js/24f52bd6.cba92751.js",
          "hash": "a943f246135cc577",
          "publicPath": "/assets/js/24f52bd6.cba92751.js"
        }
      ]
    },
    "3560": {
      "js": [
        {
          "file": "assets/js/4a2ec5cd.9cb064bc.js",
          "hash": "525b526aa40c1d4f",
          "publicPath": "/assets/js/4a2ec5cd.9cb064bc.js"
        }
      ]
    },
    "3586": {
      "js": [
        {
          "file": "assets/js/e4a51e60.bf61d15b.js",
          "hash": "1f7b1138bf64b65e",
          "publicPath": "/assets/js/e4a51e60.bf61d15b.js"
        }
      ]
    },
    "3594": {
      "js": [
        {
          "file": "assets/js/8a54e505.465ccef9.js",
          "hash": "7baee1167cd0ee52",
          "publicPath": "/assets/js/8a54e505.465ccef9.js"
        }
      ]
    },
    "4015": {
      "js": [
        {
          "file": "assets/js/a373d53b.a60e6e8a.js",
          "hash": "ddefc80f2f19e427",
          "publicPath": "/assets/js/a373d53b.a60e6e8a.js"
        }
      ]
    },
    "4055": {
      "js": [
        {
          "file": "assets/js/085c9425.99092b12.js",
          "hash": "97482470298c95e0",
          "publicPath": "/assets/js/085c9425.99092b12.js"
        }
      ]
    },
    "4085": {
      "js": [
        {
          "file": "assets/js/c47eb0e6.4113d96f.js",
          "hash": "d5d3d17033a681d8",
          "publicPath": "/assets/js/c47eb0e6.4113d96f.js"
        }
      ]
    },
    "4172": {
      "js": [
        {
          "file": "assets/js/4f6c828f.810d9ee5.js",
          "hash": "523ed82c9e0535b7",
          "publicPath": "/assets/js/4f6c828f.810d9ee5.js"
        }
      ]
    },
    "4188": {
      "js": [
        {
          "file": "assets/js/aef901ed.f762053e.js",
          "hash": "0ee5d723e2f30ab9",
          "publicPath": "/assets/js/aef901ed.f762053e.js"
        }
      ]
    },
    "4230": {
      "js": [
        {
          "file": "assets/js/233375e9.20031a31.js",
          "hash": "56f13f9f7fe7c356",
          "publicPath": "/assets/js/233375e9.20031a31.js"
        }
      ]
    },
    "4279": {
      "js": [
        {
          "file": "assets/js/df203c0f.c1806389.js",
          "hash": "f8ceaf4a643935e1",
          "publicPath": "/assets/js/df203c0f.c1806389.js"
        }
      ]
    },
    "4498": {
      "js": [
        {
          "file": "assets/js/582942cb.ee41c406.js",
          "hash": "17ffcf221b0d10d7",
          "publicPath": "/assets/js/582942cb.ee41c406.js"
        }
      ]
    },
    "4540": {
      "js": [
        {
          "file": "assets/js/763f1189.e2931744.js",
          "hash": "442c736ef8c4858f",
          "publicPath": "/assets/js/763f1189.e2931744.js"
        }
      ]
    },
    "4582": {
      "js": [
        {
          "file": "assets/js/bcaf8276.93ded7bd.js",
          "hash": "fbd858986bda654d",
          "publicPath": "/assets/js/bcaf8276.93ded7bd.js"
        }
      ]
    },
    "4583": {
      "js": [
        {
          "file": "assets/js/1df93b7f.5ba0aa8e.js",
          "hash": "e0d2fcab6b3fa0da",
          "publicPath": "/assets/js/1df93b7f.5ba0aa8e.js"
        }
      ]
    },
    "4662": {
      "js": [
        {
          "file": "assets/js/4662.a086e58e.js",
          "hash": "ecbd7b0c03260ac0",
          "publicPath": "/assets/js/4662.a086e58e.js"
        }
      ]
    },
    "4711": {
      "js": [
        {
          "file": "assets/js/612bf423.81991c2d.js",
          "hash": "15170158c4c27010",
          "publicPath": "/assets/js/612bf423.81991c2d.js"
        }
      ]
    },
    "4787": {
      "js": [
        {
          "file": "assets/js/3720c009.d2aad450.js",
          "hash": "9b503262c00b9ead",
          "publicPath": "/assets/js/3720c009.d2aad450.js"
        }
      ]
    },
    "5354": {
      "js": [
        {
          "file": "assets/js/runtime~main.d3f0ef69.js",
          "hash": "453d63d9ee8f13c7",
          "publicPath": "/assets/js/runtime~main.d3f0ef69.js"
        }
      ]
    },
    "5475": {
      "js": [
        {
          "file": "assets/js/f5e764de.1148f17d.js",
          "hash": "b4253ed33890513c",
          "publicPath": "/assets/js/f5e764de.1148f17d.js"
        }
      ]
    },
    "5570": {
      "js": [
        {
          "file": "assets/js/7dbdc362.f204801f.js",
          "hash": "69c07dfcf66b7dbe",
          "publicPath": "/assets/js/7dbdc362.f204801f.js"
        }
      ]
    },
    "5605": {
      "js": [
        {
          "file": "assets/js/c5936f55.86ba2648.js",
          "hash": "5fa62df7d52c6710",
          "publicPath": "/assets/js/c5936f55.86ba2648.js"
        }
      ]
    },
    "5655": {
      "js": [
        {
          "file": "assets/js/21c91d75.2bba9ba3.js",
          "hash": "15f3b7a665081af3",
          "publicPath": "/assets/js/21c91d75.2bba9ba3.js"
        }
      ]
    },
    "5742": {
      "js": [
        {
          "file": "assets/js/aba21aa0.4f919c7e.js",
          "hash": "1ad29d35e5b94475",
          "publicPath": "/assets/js/aba21aa0.4f919c7e.js"
        }
      ]
    },
    "5950": {
      "js": [
        {
          "file": "assets/js/cdf69b89.321fda80.js",
          "hash": "c6b8868a24c603cc",
          "publicPath": "/assets/js/cdf69b89.321fda80.js"
        }
      ]
    },
    "6186": {
      "js": [
        {
          "file": "assets/js/566e4fb3.34370f48.js",
          "hash": "0920bde71701db66",
          "publicPath": "/assets/js/566e4fb3.34370f48.js"
        }
      ]
    },
    "6860": {
      "js": [
        {
          "file": "assets/js/05f37680.604f05bf.js",
          "hash": "5612db97edd74d79",
          "publicPath": "/assets/js/05f37680.604f05bf.js"
        }
      ]
    },
    "6980": {
      "js": [
        {
          "file": "assets/js/313b23b7.eb3ecc93.js",
          "hash": "d85872cc3a564faf",
          "publicPath": "/assets/js/313b23b7.eb3ecc93.js"
        }
      ]
    },
    "7098": {
      "js": [
        {
          "file": "assets/js/a7bd4aaa.1e14bda9.js",
          "hash": "c524c2104ba758b0",
          "publicPath": "/assets/js/a7bd4aaa.1e14bda9.js"
        }
      ]
    },
    "7252": {
      "js": [
        {
          "file": "assets/js/c6854a93.838f5fdf.js",
          "hash": "e42c0901672ab3c3",
          "publicPath": "/assets/js/c6854a93.838f5fdf.js"
        }
      ]
    },
    "7639": {
      "js": [
        {
          "file": "assets/js/2e9f3641.3f468be1.js",
          "hash": "7b8c79d33a0c4050",
          "publicPath": "/assets/js/2e9f3641.3f468be1.js"
        }
      ]
    },
    "7826": {
      "js": [
        {
          "file": "assets/js/f857cf71.a33b88c2.js",
          "hash": "35415e50ea938ced",
          "publicPath": "/assets/js/f857cf71.a33b88c2.js"
        }
      ]
    },
    "7946": {
      "js": [
        {
          "file": "assets/js/b5b50283.de32fb48.js",
          "hash": "bc8ecb11ac02c9ca",
          "publicPath": "/assets/js/b5b50283.de32fb48.js"
        }
      ]
    },
    "8401": {
      "js": [
        {
          "file": "assets/js/17896441.6543e37e.js",
          "hash": "ec31a833ee4d5b87",
          "publicPath": "/assets/js/17896441.6543e37e.js"
        }
      ]
    },
    "8463": {
      "js": [
        {
          "file": "assets/js/276632bd.464798b7.js",
          "hash": "e6e571575617dac3",
          "publicPath": "/assets/js/276632bd.464798b7.js"
        }
      ]
    },
    "8722": {
      "js": [
        {
          "file": "assets/js/4ba3f97a.d5b05cf0.js",
          "hash": "79c2c5a74718c6ac",
          "publicPath": "/assets/js/4ba3f97a.d5b05cf0.js"
        }
      ]
    },
    "8746": {
      "js": [
        {
          "file": "assets/js/78ba771b.013d3cda.js",
          "hash": "4375002fbee11ae6",
          "publicPath": "/assets/js/78ba771b.013d3cda.js"
        }
      ]
    },
    "8792": {
      "js": [
        {
          "file": "assets/js/main.c8f4fb14.js",
          "hash": "8f3a5a2a2dba7353",
          "publicPath": "/assets/js/main.c8f4fb14.js"
        }
      ]
    },
    "9048": {
      "js": [
        {
          "file": "assets/js/a94703ab.44b5ce7d.js",
          "hash": "dc7d956bf5e9beaf",
          "publicPath": "/assets/js/a94703ab.44b5ce7d.js"
        }
      ]
    },
    "9067": {
      "js": [
        {
          "file": "assets/js/898514b1.3d140b5d.js",
          "hash": "44b06b62872043e2",
          "publicPath": "/assets/js/898514b1.3d140b5d.js"
        }
      ]
    },
    "9178": {
      "js": [
        {
          "file": "assets/js/9178.84340acf.js",
          "hash": "29f7cef0f4443232",
          "publicPath": "/assets/js/9178.84340acf.js"
        }
      ]
    },
    "9634": {
      "js": [
        {
          "file": "assets/js/8ae7243c.2fce7b10.js",
          "hash": "d770c9409a988d1a",
          "publicPath": "/assets/js/8ae7243c.2fce7b10.js"
        }
      ]
    },
    "9647": {
      "js": [
        {
          "file": "assets/js/5e95c892.d5dab229.js",
          "hash": "4b6a5469dcf7e576",
          "publicPath": "/assets/js/5e95c892.d5dab229.js"
        }
      ]
    }
  }
}